{
  "Name": "Plucker",
  "Inherits": "Scavenger",
  "Type": "Template",
  "UsesClass": "Skirmisher",
  "Traits": [
    {
      "Name": "Golden Burden",
      "Description": "Has evasion against characters carrying valuables."
    }
  ],
  "Actions": [
    {
      "Name": "Lighten Load",
      "ActionCost": 1,
      "Recharge": 5,
      "Tags": [ "melee attack" ],
      "Hit": "2 piercing damage once for each valuables token the target is carrying.",
      "Miss": "1 piercing damage once for each valuables token the target is carrying.",
      "Effect": "The Plucker may teleport 3 before this attack."
    }
  ]
}